network3_homer/__init__.py
network3_homer/csv.j2
network3_homer/datatable_footer.j2
network3_homer/datatable_header.j2
network3_homer/html.j2
network3_homer/md.j2
network3_homer/mindmap.j2
network3_homer/network3_homer.py
network3_homer/script.py
network3_homer-0.1.1.dist-info/entry_points.txt
network3_homer-0.1.1.dist-info/WHEEL
network3_homer-0.1.1.dist-info/METADATA
network3_homer-0.1.1.dist-info/RECORD
